        <dependency>
           <groupId>eclipse</groupId>
           <artifactId>eclipse-jdt</artifactId>
           <version>3.0.0</version>
           <url>http://eclipse.org/</url>
        </dependency>
	    <dependency>
           <groupId>eclipse</groupId>
           <artifactId>eclipse-resources</artifactId>
           <version>3.0.0</version>
           <url>http://eclipse.org/</url>
        </dependency>
	    <dependency>
  	       <groupId>eclipse</groupId>
           <artifactId>eclipse-runtime</artifactId>
           <version>3.0.0</version>
           <url>http://eclipse.org/</url>
        </dependency>
		<dependency>
           <groupId>eclipse</groupId>
           <artifactId>eclipse-jdtcore</artifactId>
           <version>3.0.0</version>
           <url>http://eclipse.org/</url>
        </dependency>
        <dependency>
           <groupId>eclipse</groupId>
           <artifactId>eclipse-team-ui</artifactId>
           <version>3.0.0</version>
           <url>http://eclipse.org/</url>
        </dependency>
        <dependency>
           <groupId>eclipse</groupId>
           <artifactId>eclipse-dtcore</artifactId>
           <version>3.0.0</version>
           <url>http://eclipse.org/</url>
        </dependency>
        <dependency>
           <groupId>eclipse</groupId>
           <artifactId>eclipse-dtui</artifactId>
           <version>3.0.0</version>
           <url>http://eclipse.org/</url>
        </dependency>
        <dependency>
           <groupId>eclipse</groupId>
           <artifactId>eclipse-launching</artifactId>
           <version>3.0.0</version>
           <url>http://eclipse.org/</url>
        </dependency>
	    <dependency>
	       <groupId>eclipse</groupId>
           <artifactId>eclipse-jface</artifactId>
           <version>3.0.0</version>
           <url>http://eclipse.org/</url>
        </dependency>
	    <dependency>
	       <groupId>eclipse</groupId>
           <artifactId>eclipse-jfacetext</artifactId>
           <version>3.0.0</version>
           <url>http://eclipse.org/</url>
        </dependency>
	    <dependency>
	       <groupId>eclipse</groupId>
           <artifactId>eclipse-text</artifactId>
           <version>3.0.0</version>
           <url>http://eclipse.org/</url>
        </dependency>
	    <dependency>
	       <groupId>eclipse</groupId>
           <artifactId>eclipse-editors</artifactId>
           <version>3.0.0</version>
           <url>http://eclipse.org/</url>
        </dependency>
	    <dependency>
	       <groupId>eclipse</groupId>
           <artifactId>eclipse-swt</artifactId>
           <version>3.0.0</version>
           <url>http://eclipse.org/</url>
        </dependency>
	    <dependency>
	       <groupId>eclipse</groupId>
           <artifactId>eclipse-texteditor</artifactId>
           <version>3.0.0</version>
           <url>http://eclipse.org/</url>
        </dependency>
	    <dependency>
	       <groupId>eclipse</groupId>
           <artifactId>eclipse-workbench</artifactId>
           <version>3.0.0</version>
           <url>http://eclipse.org/</url>
        </dependency>
        <dependency>
	       <groupId>eclipse</groupId>
           <artifactId>eclipse-views</artifactId>
           <version>3.0.0</version>
           <url>http://eclipse.org/</url>
        </dependency>
        <dependency>
        	<groupId>eclipse</groupId>	
        	<artifactId>eclipse-externaltools</artifactId>
        	<version>3.0.0</version>
        	<url>http://eclipse.org/</url>
        </dependency>
    	<dependency>
            <groupId>eclipse</groupId>	
        	<artifactId>eclipse-help</artifactId>
        	<version>3.0.0</version>
        	<url>http://eclipse.org/</url>
        </dependency>
        <dependency>
            <groupId>eclipse</groupId>	
        	<artifactId>eclipse-variables</artifactId>
        	<version>3.0.0</version>
        	<url>http://eclipse.org/</url>
        </dependency>
        <dependency>
            <groupId>eclipse</groupId>	
        	<artifactId>eclipse-osgi</artifactId>
        	<version>3.0.0</version>
        	<url>http://eclipse.org/</url>
        </dependency>
        <dependency>
        	<groupId>eclipse</groupId>	
        	<artifactId>eclipse-helpbase</artifactId>
        	<version>3.0.0</version>
        	<url>http://eclipse.org/</url>
        </dependency>
    	<dependency>
        	<groupId>eclipse</groupId>	
        	<artifactId>eclipse-ide</artifactId>
        	<version>3.0.0</version>
        	<url>http://eclipse.org/</url>
        </dependency>
    	<dependency>
        	<groupId>eclipse</groupId>	
        	<artifactId>eclipse-forms</artifactId>
        	<version>3.0.0</version>
        	<url>http://eclipse.org/</url>
        </dependency>